{
  "facilities": [
    {
      "id": 1,
      "name": "Meeting Room A",
      "photoUrl": "assets/meeting_room.jpg",
      "description": "Lorem ipsum dolor sit amet, ea homero rationibus per. Cum enim electram at.\nCu vis omittam persecuti, eam ex legimus alienum omittantur.\nError laudem explicari ea pri, id vel maluisset instructior.",
      "price": 10
    },
    {
      "id": 2,
      "name": "Meeting Room B",
      "photoUrl": "assets/meeting_room2.jpg",
      "description": "Lorem ipsum dolor sit amet, ea homero rationibus per. Cum enim electram at.\nCu vis omittam persecuti, eam ex legimus alienum omittantur.\nError laudem explicari ea pri, id vel maluisset instructior.",
      "price": 10
    },
    {
      "id": 3,
      "name": "Meeting Point (Full)",
      "description": "Lorem ipsum dolor sit amet, ea homero rationibus per. Cum enim electram at.\nCu vis omittam persecuti, eam ex legimus alienum omittantur.\nError laudem explicari ea pri, id vel maluisset instructior.",
      "price": 30,
      "group": [
        {
          "id": 31,
          "name": "Meeting Point (Space A)",
          "photoUrl": "assets/meeting_room3.jpg",
          "description": "Lorem ipsum dolor sit amet, ea homero rationibus per. Cum enim electram at.\nCu vis omittam persecuti, eam ex legimus alienum omittantur.\nError laudem explicari ea pri, id vel maluisset instructior.",
          "price": 15
        },
        {
          "id": 32,
          "name": "Meeting Point (Space B)",
          "photoUrl": "assets/meeting_room3.jpg",
          "description": "Lorem ipsum dolor sit amet, ea homero rationibus per. Cum enim electram at.\nCu vis omittam persecuti, eam ex legimus alienum omittantur.\nError laudem explicari ea pri, id vel maluisset instructior.",
          "price": 20
        }
      ]
    },
    {
      "id": 4,
      "name": "Basketball Court",
      "photoUrl": "assets/basketball_court.jpg",
      "description": "Lorem ipsum dolor sit amet, ea homero rationibus per. Cum enim electram at.\nCu vis omittam persecuti, eam ex legimus alienum omittantur.\nError laudem explicari ea pri, id vel maluisset instructior.",
      "price": 25
    }
  ],
  "events": [
    {
      "id": 1,
      "facilityId": 1,
      "title": "Meeting",
      "start": "2018-03-12T10:00:00",
      "end": "2018-03-12T12:00:00"
    },
    {
      "id": 2,
      "facilityId": 3,
      "title": "Lunch",
      "start": "2018-03-12T12:00:00"
    },
    {
      "id": 3,
      "facilityId": 2,
      "title": "Meeting",
      "start": "2018-03-12T14:00:00"
    },
    {
      "id": 4,
      "facilityId": 31,
      "title": "Happy Hour",
      "start": "2018-03-12T17:00:00"
    },
    {
      "id": 5,
      "facilityId": 4,
      "title": "Dinner",
      "start": "2018-03-12T20:00:00"
    },
    {
      "id": 6,
      "facilityId": 32,
      "title": "Birthday Party",
      "start": "2018-03-13T07:00:00"
    },
    {
      "facilityId": 4,
      "title": "test 2",
      "start": "2018-03-05",
      "duration": 1,
      "allDay": true,
      "end": "2018-03-06",
      "id": 7
    },
    {
      "facilityId": 4,
      "title": "test 2",
      "start": "2018-03-05T09:00:00",
      "duration": 1,
      "allDay": false,
      "end": "2018-03-05T10:00:00",
      "id": 8
    },
    {
      "facilityId": 4,
      "title": "test",
      "start": "2018-03-05T11:00:00",
      "duration": 1,
      "allDay": false,
      "end": "2018-03-05T12:00:00",
      "id": 9
    },
    {
      "facilityId": 1,
      "title": "test 2",
      "start": "2018-03-12",
      "duration": 1,
      "allDay": true,
      "end": "2018-03-13",
      "id": 10
    },
    {
      "facilityId": 2,
      "title": "test 2",
      "start": "2018-03-13T08:00:00",
      "duration": 1,
      "allDay": false,
      "end": "2018-03-13T09:00:00",
      "id": 11
    },
    {
      "facilityId": 2,
      "title": "test",
      "start": "2018-03-13T09:00:00",
      "duration": 1,
      "allDay": false,
      "end": "2018-03-13T10:00:00",
      "id": 12
    },
    {
      "facilityId": 2,
      "title": "test 2",
      "start": "2018-03-13",
      "duration": 1,
      "allDay": true,
      "end": "2018-03-14",
      "id": 13
    },
    {
      "facilityId": 2,
      "title": "test 2",
      "start": "2018-03-14",
      "duration": 6,
      "allDay": true,
      "end": "2018-03-20",
      "id": 14
    }
  ]
}